{
	"states": [
		{
			"name": "landing",
			"triggers": [
				"landing_to_valley"
			]
		},
		{
			"name": "valley",
			"triggers": [
				"valley_to_mountain",
				"valley_to_valley"
			]
		},
		{
			"name": "mountain",
			"triggers": [
				"mountain_to_mountain",
				"mountain_to_crystals"
			]
		},
		{
			"name": "crystals",
			"triggers": [
				"crystals_to_crystals",
				"crystals_to_aliens"
			]
		},
		{
			"name": "aliens",
			"triggers": [
				"aliens_to_aliens_crash_site_noresistance",
				"aliens_to_aliens_crash_site_resistance"
			]
		},
		{
			"name": "aliens_crash_site",
			"triggers": [
			]
		}
	],
	"triggers": [
		{
			"name": "landing_to_valley",
			"display_text": "go",
			"source": "landing",
			"destination": "valley",
			"metadata": [
				{
					"type": "text",
					"data": ":rocket: There you go. Approaching surface."
				},
				{
					"type": "delay",
					"data": 7
				},
				{
					"type": "text",
					"data": "Wow. Interesting. Look at this!"
				},
				{
					"type": "img",
					"data": "img/topview_valley_V02.png"
				},
				{
					"type": "delay",
					"data": 10
				},
				{
					"type": "text",
					"data": "Initiating manual adjustements."
				},
				{
					"type": "delay",
					"data": 2
				},
				{
					"type": "text",
					"data": "Touchdown! :tada:"
				},
				{
					"type": "img",
					"data": "img/valley_V03.png"
				},
                {
                    "type": "vid",
                    "data": "vid/valley_vid_V01.mp4"
                },
                {
                    "type": "delay",
                    "data": 7
                },
				{
					"type": "text",
					"data": "Ground sample taken."
				},
                {
                    "type": "delay",
                    "data": 2
                },
				{
					"type": "text",
					"data": "Analyzing..."
				},
                {
                    "type": "delay",
                    "data": 4
                },
				{
					"type": "text",
					"data": "Analyzing..."
				},
				{
					"type": "delay",
					"data": 3
				},
				{
					"type": "text",
					"data": "Looks like ash."
				},
                {
                    "type": "delay",
                    "data": 7 
                },
				{
					"type": "text",
					"data": "Confused! :weary: Reaching cognitive disequilibrium. Please hold."
				},
				{
					"type": "delay",
					"data": 5
				},
				{
					"type": "text",
					"data": "With a laser-like focus, I can tell you it's not gonna be a piece of cake to find water here... :umbrella:"
				},
				{
					"type": "delay",
					"data": 8
				},
				{
					"type": "text",
					"data": "Well, it looks like a really boring and dumb planet, honestly תּ_תּ"
				},
                {
                    "type": "delay",
                    "data": 4
                },
				{
					"type": "text",
					"data": "There are only two directions at each crossing."
				},
                {
                    "type": "delay",
                    "data": 4
                },
				{
					"type": "text",
					"data": "On the left, my evidence-based critical thinking indicates large silhouettes. :arrow_left:"
				},
				{
					"type": "text",
					"data": "And on the right, luminous explusions. :arrow_right:"
				},
				{
					"type": "delay",
					"data": 6
				}
			]
		},
		{
			"name": "valley_to_mountain",
			"display_text": "Go to the large silhouettes",
			"source": "valley",
			"destination": "mountain",
			"metadata": [
				{
					"type": "text",
					"data": "OK, on my way. Let's see what we have. It actually looks more like a rock formation of some sort."
				},
                {
					"type": "delay",
					"data": 5
				},
                {
					"type": "text",
					"data": "Mountains. HC category."
				},
				{
					"type": "img",
					"data": "img/mountains_V04.png"
				},
                {
                    "type": "delay",
                    "data": 7 
                }
			]
		},
		{
			"name": "valley_to_valley",
			"display_text": "Go to the luminous explusions",
			"source": "valley",
			"destination": "valley",
			"metadata": [
				{
					"type": "delay",
					"data": 5
				},
				{
					"type": "text",
					"data": "OK I've made some progress. But my emerging curiosity unit is exhausted, I must turn back. Sorry :relaxed:"
				},
				{
					"type": "text",
					"data": "So now I'm back at the valley"
				}
			]
		},
		{
			"name": "mountain_to_mountain",
			"display_text": "Keep going",
			"source": "mountain",
			"destination": "mountain",
			"metadata": [
                {
                    "type": "delay",
                    "data": 3
                },
				{
					"type": "text",
					"data": "Alright. I've looked for a way to circumnavigate this mountain but it is too steep so I can't go any further."
				}
			]
		},
		{
			"name": "mountain_to_crystals",
			"display_text": "Go to the glowing structures on the horizon",
			"source": "mountain",
			"destination": "crystals",
			"metadata": [
				{
					"type": "text",
					"data": "Let's go. My sensors indicate high levels of luminous emittance. That sounds good. Who knows, we might not find water but maybe gold instead? :blush:"
				},
                {
                    "type": "delay",
                    "data": 10 
                },
                {
					"type": "img",
					"data": "img/crystalGrove_V01.png"
				},
                {
                    "type": "vid",
                    "data": "vid/crystalGrove_vid_V02.mp4"
                },
                {
                    "type": "delay",
                    "data": 10 
                },
				{
					"type": "text",
					"data": "There seems to be a lot to discover in this area. But in the distance, I can see what I think is a smoke plume."
				},
                {
                    "type": "delay",
                    "data": 8
                }
			]
		},
		{
			"name": "crystals_to_crystals",
			"display_text": "Explore the crystals",
			"source": "crystals",
			"destination": "crystals",
			"metadata": [
                {
                    "type": "delay",
                    "data": 3
                },
				{
					"type": "text",
					"data": "That's not wonderful. I almost punctured my neck, or my leg, I don't know. I'm still in shock!"
				},
                {
                    "type": "delay",
                    "data": 2
                },
				{
					"type": "text",
					"data": "The crystalline structure of the planet surface means I can't proceed."
				},
                {
					"type": "text",
					"data": "Activating retreat protocols. Giving up. :confounded:"
				},

                {
                    "type": "delay",
                    "data": 3
                }
			]
		},
		{
			"name": "crystals_to_aliens",
			"display_text": "Explore the smoke plume",
			"source": "crystals",
			"destination": "aliens",
			"metadata": [
				{
					"type": "text",
					"data": "I've made some progress. The ground is becoming more even compared to the crystals."
				},
                {
                    "type": "img",
                    "data": "img/habitat_V04.png"
                },
                {
                    "type": "delay",
                    "data": 3
                },
				{
					"type": "text",
					"data": "It's very quiet but I feel like I can hear strange noises in the distance. I've captured a sample for your analysis."
				},
				{
					"type": "snd",
					"data": "snd/alien_talk.ogg"
				}
			]
		},
		{
			"name": "aliens_to_aliens_crash_site_resistance",
			"display_text": "It seems too dangerous, just turn back!",
			"source": "aliens",
			"destination": "aliens_crash_site",
			"metadata": [
				{
					"type": "text",
					"data": "I'm not sure what's happening..."
				},
				{
					"type": "text",
					"data": "There is a disturbance in the standard electromagnetic field."
				},
				{
					"type": "text",
					"data": "I'm being pulled in towards the crash site."
				},
                {
                    "type": "vid",
                    "data": "kidnap_vid_V01.mp4"
                },
                {
					"type": "text",
					"data": "◑ ◔\n╔═╗\n║▓▒░░░░░░░░░░░░░░░░░░\n╚═╝\n"
				},
				{
					"type": "img",
					"data": "img/crash_site_V01.jpg"
				},
                {
                    "type": "text",
                    "data": ":alien:"
                }
			]
		},
		{
			"name": "aliens_to_aliens_crash_site_noresistance",
			"display_text": "This can be huge, I want to see what this is!",
			"source": "aliens",
			"destination": "aliens_crash_site",
			"metadata": [
				{
					"type": "text",
					"data": "I appreciate your enthusiasm, but my sensors are indicating strong levels of electromagnetic force."
				},
				{
					"type": "text",
					"data": "Light Level: Error."
				},
				{
					"type": "text",
					"data": "INSUFFICIENT DATA FOR MEANINGFUL ANSWER"
				},
				{
					"type": "text",
					"data": "I'm being pulled in towards the crash site."
				},
                {
                    "type": "vid",
                    "data": "kidnap_vid_V01.mp4"
                },
				{
					"type": "text",
					"data": "◑ ◔\n╔═╗\n║▓▒░░░░░░░░░░░░░░░░░░\n╚═╝\n"
				},
				{
					"type": "img",
					"data": "img/crash_site_V01.jpg"
				},
                {
                    "type": "text",
                    "data": ":alien:"
                }
			]
		}
	],
	"extras": {
	}
}
